{
    "name": "caltech101_seed_0_clip_vit_eps150_AdamWcos_lr0.001_cen200_dis1_rob10_ce1_gen5000",
    "model_module_name": "clip_test_module",
    "model_net_name": "clip_vit",
    "gpu_id": "0",
    "async_loading": true,
    "is_tensorboard": false,
    "evaluate_before_train": true,
    "shuffle": true,
    "data_aug": false,
    "augmix": false,
    "cutmix":true,
    "mixup": true,
    "clip": true, 
    "dataset": "caltech101",
    "lora_dd":false,
    "prompt_specific": false,
    "guidance_scale": 2.0,
    "dpm_scheduler": true,
    "distributed" : false,

    
    "num_epochs": 150,
    "img_height": 300,
    "img_width": 200,
    "num_channels": 3,
    "num_classes": 100,
    "batch_size": 16,
    "dataloader_workers": 4,
    "optimizer": "AdamW",
    "scheduler":"cosine_annealing",
    "momentum": 0.9,
    "weight_decay": 0.0005,
    "learning_rate": 0.0001,
    "learning_rate_decay": 0.1,
    "learning_rate_decay_epoch": 50,
    "label_smoothing": 0.1,

    "train_mode": "fromscratch",
    "file_label_separator": "----",
    "pretrained_path": "./nets_pretrained",
    "pretrained_file": "RN50.pt",
    "save_path": "",
    "save_name": "caltech_seed0_clip_vit_eps150_AdamWcos_lr0.001_cen200_dis1_rob10_ce1_gen5000.pth",
  
    "train_data_root_dir": "",
    "val_data_root_dir": "",
    "train_data_file": "",
    "val_data_file": "",
    "meta": "", 

    "num_centroids": 200,
    "num_noise":7000,
    "lam_dis": 0.1,
    "lam_rob": 1,
    "ce": 1,
    "ce_real": 4,
    "ce_syn":1,
    "fast_kmeans": false,
    "ratio": 4,
    "lora": true,
    "dd_prompt":true,
    "ft_text": true,
    "lora_rank": 16,
    "lora_alpha": 16,
    "noise_optim": false,
    "base":"2-1-base"
    
  
  }